m_pool/__init__.py
m_pool/_version.py
m_pool/axis_obj.py
m_pool/axis_pool.py
m_pool/matrix_obj.py
m_pool/matrix_pool.py
m_pool/transform.py
m_pool/examples/CHECK_matrix.pool
m_pool/examples/N2O4_MMH_matrix.pool
m_pool/examples/interp_chk.py
m_pool/examples/iter_chk.py
m_pool/examples/pool_chk.py
m_pool/examples/read_pool.py
m_pool/examples/slice_chk.py
m_pool/examples/solve_max_chk.py
m_pool/examples/solve_min_chk.py
m_pool/tests/__init__.py
m_pool/tests/test_matrix_pool.py
m_pool-0.0.2.dist-info/DESCRIPTION.rst
m_pool-0.0.2.dist-info/METADATA
m_pool-0.0.2.dist-info/RECORD
m_pool-0.0.2.dist-info/WHEEL
m_pool-0.0.2.dist-info/metadata.json
m_pool-0.0.2.dist-info/top_level.txt
