Metadata-Version: 2.0
Name: m-pool
Version: 0.0.2
Summary: A wrapper for numpy arrays providing named axes, interpolation, iteration, disk persistence and numerical calcs
Home-page: http://m_pool.readthedocs.org/en/latest/
Author: Charlie Taylor
Author-email: cet@appliedpython.com
License: GPL-3
Download-URL: https://github.com/sonofeft/M_Pool
Keywords: m_pool setuptools development
Platform: any
Classifier: Development Status :: 3 - Alpha
Classifier: Operating System :: OS Independent
Classifier: Intended Audience :: Developers
Classifier: Intended Audience :: End Users/Desktop
Classifier: Topic :: Software Development :: Build Tools
Classifier: License :: OSI Approved :: GNU General Public License v3 (GPLv3)
Classifier: Programming Language :: Python :: 2.7
Provides-Extra: test
Provides-Extra: dev
Requires-Dist: coverage
Requires-Dist: future
Requires-Dist: numexpr
Requires-Dist: numpy
Requires-Dist: scipy
Provides-Extra: dev
Requires-Dist: check-manifest; extra == 'dev'
Provides-Extra: test
Requires-Dist: coverage; extra == 'test'
